pygments_crbasic.py
pygments_crbasic-0.1.0.dist-info/LICENCE
pygments_crbasic-0.1.0.dist-info/METADATA
pygments_crbasic-0.1.0.dist-info/WHEEL
pygments_crbasic-0.1.0.dist-info/entry_points.txt
pygments_crbasic-0.1.0.dist-info/top_level.txt
pygments_crbasic-0.1.0.dist-info/RECORD
