Metadata-Version: 2.1
Name: pygments_crbasic
Version: 0.1.0
Summary: "A pygments lexer for campbell scientific's crbasic language"
Home-page: https://github.com/jkittner/pygments-crbasic
Author: Jonas Kittner
Author-email: jonas.kittner@ruhr-uni-bochum.de
License: MIT
Classifier: License :: OSI Approved :: MIT License
Classifier: Programming Language :: Python :: 3
Classifier: Programming Language :: Python :: 3 :: Only
Classifier: Programming Language :: Python :: Implementation :: CPython
Requires-Python: >=3.8
License-File: LICENCE
Requires-Dist: pygments
